<?xml version="1.0" encoding="UTF-8"?>

<additional>
    
    <tlLogic id="C" type="static" programID="fix-time" offset="0">
        <phase duration="25" state="GrGrGrrGrrGrGrGrrGrrrrrr"/>        
        <phase duration="4"  state="yrGryrrGrryrGryrrGrrrrrr"/>
        <phase duration="3"  state="rrGrrrrGrrrrGrrrrGrrrrrr"/>
                        
        <phase duration="25" state="rGGGrrrGrrrGGGrrrGrrrGrG"/>
        <phase duration="4"  state="ryGyrrrGrrryGyrrrGrrryry"/>
        <phase duration="3"  state="rrGrrrrGrrrrGrrrrGrrrrrr"/>
        
        <phase duration="25" state="rrGrrGrGrGrrGrrGrGrGrrrr"/>   
        <phase duration="4"  state="rrGrryrGryrrGrryrGryrrrr"/>  
        <phase duration="3"  state="rrGrrrrGrrrrGrrrrGrrrrrr"/>      
        
        <phase duration="25" state="rrGrrrGGGrrrGrrrGGGrGrGr"/>
        <phase duration="4"  state="rrGrrryGyrrrGrrryGyryryr"/>
        <phase duration="3"  state="rrGrrrrGrrrrGrrrrGrrrrrr"/>        
    </tlLogic>
    
    <tlLogic id="C" type="static" programID="adaptive-time" offset="-10">
        <phase duration="100" state="rrrrrrrrrrrrrrrrrrrrrrrr"/>
    </tlLogic>
    
</additional>
